6526 CIA.srcs/sources_1/new/tod.v
`timescale 1ns / 1ps
//////////////////////////////////////////////////////////////////////////////////
// Company: 
// Engineer: 
// 
// Create Date: 01/26/2020 05:32:22 PM
// Design Name: 
// Module Name: tod
// Project Name: 
// Target Devices: 
// Tool Versions: 
// Description: 
// 
// Dependencies: 
// 
// Revision:
// Revision 0.01 - File Created
// Additional Comments:
// 
//////////////////////////////////////////////////////////////////////////////////



module TOD(
  input wire reset_b,
  input wire Hz50,
  input wire TOD_clk,
  input wire select_b,
  input	wire rwb,
  input wire phi2,
  input wire [3:0] rs,
  output reg [31:0] tod_latch,
  input wire [7:0] db_in
);
  //INTERNAL REGISTERS
  reg [2:0] tod_tick_counter;
  reg [31:0] tod;
  reg [31:0] alarm;
  reg tod_run;
  
  //wires
  wire  wr = !rwb & !select_b;
  wire  rd = rwb & !select_b;
  
  //Evaluate carry bits - combinational logic
  //10th sec
  assign c1= tod[3:0]>=9?1:0;
  //seconds
  assign c2= tod[11:8]>=9&&c1?1:0;
  assign c3= tod[15:12]>=5&&c2?1:0;
  //minutes
  assign c4= tod[19:16]>=9&&c3?1:0;
  assign c5= tod[23:20]>=5&&c4?1:0;
  //hours
  assign c6= tod[27:24]>=9&&c5?1:0;

  
  always @(negedge TOD_clk)
  begin
    if(!reset_b)
      begin
        tod_run<=1;
        tod_tick_counter=3'h6;
        tod<=32'h01000000;
        //tod_latch<=32'h01000000;
        //alarm <=32'h00000000;
      end
    else if (tod_run)
      begin
        tod_latch[31:0]<=tod[31:0];
        tod_tick_counter = tod_tick_counter -1;
      end
      if(!tod_tick_counter)
        begin
          if(Hz50)
            tod_tick_counter=3'h5;
          else
            tod_tick_counter=3'h6;
            
          //Add carry bit from prior stage
                   
          
                        
          
          
          
      
      
          //reset to 0 if max digit is reached
          if(c1)
            tod[3:0]<=4'd0;
          else
            tod[3:0]<=tod[3:0]+4'd1;
            
          if(c2)
            tod[11:8]<=4'd0;
          else
            tod[11:8]<=tod[11:8]+c1;
            
             
          if(c3)
            tod[15:12]<=4'd0;
          else
            tod[15:12]<=tod[15:12]+c2;
            
                        
          if(c4)
            tod[19:16]<=4'd0;
          else
            tod[19:16]<=tod[19:16]+c3;
                        
          if(c5)
            tod[23:20]<=4'd0;
          else
            tod[23:20]<=tod[23:20]+c4;
            
                        
          if(c6)
            tod[27:24]<=4'd0;
          else
            tod[27:24]<=tod[27:24]+c5;          
                    
          // if 13 hours set to 1
          if(tod[28:24]>=5'h13)
          tod[28:24]<=5'h01;
          
          //if 12000000 then toggle pm flag
          if(tod[28:0]==29'h12000000) tod[31]<=~tod[31];


        end
        
      //read tod latch
    else if(wr)
      begin
        case(rs)
          4'h8:
            begin
              tod[7:0]<=db_in;
              tod_run<=1;
            end
          4'h9: tod[15:8]<=db_in;
          4'ha: tod[23:16]<=db_in;
          4'hb: 
            begin
              tod[31:24]<=db_in;
              tod_run<=0;
            end
        endcase
      end
  
    end
  
    //Evaluate carry bits
  //10th sec
  //assign c1= tod[3:0]>=9?1:0;
  //seconds
  //assign c2= tod[11:8]>=9&&c1?1:0;
  //assign c3= tod[15:12]>=5&&c2?1:0;
  //minutes
  //assign c4= tod[19:16]>=9&&c3?1:0;
  //assign c5= tod[23:20]>=5&&c4?1:0;
  //hours
  //assign c6= tod[27:24]>=9&&c5?1:0;

/*   
  //RESET
  always @(negedge phi2)
    begin
    if (!reset_b)
      begin
        tod_run=0;
        tod_tick_counter=3'h0;
        tod<=32'h01000000;
        //tod<=32'h11595908;
        alarm <=23'h0;
      end
    end
*/
  //Increment TOD if tick counter
  /*
  always @(posedge TOD_clk)
    begin
      if(tod_run)
        begin
          tod_tick_counter<=tod_tick_counter+1;
          if ((!Hz50 && tod_tick_counter==3'h6)|| (Hz50 && tod_tick_counter==3'h5))
            begin
              //Reset tick counter
              tod_tick_counter<=3'h0;
            
              //Add carry bit from prior stage
              tod[3:0]<=tod[3:0]+1;
         
              tod[11:8]<=tod[11:8]+c1;
              tod[15:12]<=tod[15:12]+c2;
          
              tod[19:16]<=tod[19:16]+c3;
              tod[23:20]<=tod[23:20]+c4;
          
              tod[27:24]<=tod[27:24]+c5;
              tod[29:28]<=tod[29:28]+c6;
          
          
              //reset to 0 if max digit is reached
              if(tod[3:0]>=10) tod[3:0]<=0;
          
              if(tod[11:8]>=10) tod[11:8]<=0;
              if(tod[15:12]>=6) tod[15:12]<=0;
          
              if(tod[19:16]>=10) tod[19:16]<=0;
              if(tod[23:20]>=6) tod[23:20]<=0;
          
              if(tod[27:24]>=10) tod[27:24]<=0;
          
              // if 13 hours set to 1
              if(tod[28:24]>=5'h13)
              tod[28:24]<=5'h01;
          
              //if 12000000 then toggle pm flag
              if(tod[28:0]==29'h12000000) tod[31]<=~tod[31];
              
            end          
        end
    end

  
  always @(posedge TOD_clk) 
    begin
    //RESET (need to be based off phi2 edge, not TOD_clk)
      if (~reset_b)
        begin
          tod_run=0;
          tod_tick_counter=3'h0;
          tod<=32'h01000000;
          //tod<=32'h11595908;
          alarm <=23'h0;
        end
      //Update tod_latch on every TOD clock; not certain chip really works this way
      else if (rd && rs==4'hb)
        tod_latch[31:0]=tod[31:0];
    else if(wr)
      begin
        case(rs)
          4'h8:
            begin
              tod[7:0]<=db_in;
              tod_run<=1;
            end
          4'h9: tod[15:8]<=db_in;
          4'ha: tod[23:16]<=db_in;
          4'hb: 
            begin
              tod[31:24]<=db_in;
              tod_run<=0;
            end
        endcase
      end
      if(tod_run)
        begin
          tod_tick_counter<=tod_tick_counter+1;
          if ((!Hz50 && tod_tick_counter==3'h6)|| (Hz50 && tod_tick_counter==3'h5))
            begin
              //Reset tick counter
              tod_tick_counter<=3'h0;
            
              //Add carry bit from prior stage
              tod[3:0]<=tod[3:0]+1;
              
              tod[11:8]<=tod[11:8]+c1;
              tod[15:12]<=tod[15:12]+c2;
          
              tod[19:16]<=tod[19:16]+c3;
              tod[23:20]<=tod[23:20]+c4;
          
              tod[27:24]<=tod[27:24]+c5;
              tod[29:28]<=tod[29:28]+c6;
          
          
              //reset to 0 if max digit is reached
              if(tod[3:0]>=10) tod[3:0]<=0;
          
              if(tod[11:8]>=10) tod[11:8]<=0;
              if(tod[15:12]>=6) tod[15:12]<=0;
          
              if(tod[19:16]>=10) tod[19:16]<=0;
              if(tod[23:20]>=6) tod[23:20]<=0;
          
              if(tod[27:24]>=10) tod[27:24]<=0;
          
              // if 13 hours set to 1
              if(tod[28:24]>=5'h13)
              tod[28:24]<=5'h01;
          
              //if 12000000 then toggle pm flag
              if(tod[28:0]==29'h12000000) tod[31]<=~tod[31];
              
            end          
        end
    end
   */
endmodule

6526 CIA.srcs/sources_1/new/main.v
`timescale 10ns/10ns
module CIA(
  input  wire       phi2,
  input  wire       res_b,
  input  wire       cs_b,
  input  wire       rw,

  input  wire [3:0] rs,
  input  wire [7:0] db_in,
  output reg  [7:0] db_out,

  input  wire [7:0] pa_in,
  output reg  [7:0] pa_out,
  input  wire [7:0] pb_in,
  output reg  [7:0] pb_out,
  output reg  [7:0] ddra,
  output reg  [7:0] ddrb,
  
  input wire		tod
);
  



// Internal Registers
  reg [7:0] cra;
  reg [7:0] crb;

  //reg [15:0] timer_in;
  
// Internal Signals

  wire  rd = !cs_b & rw;
  wire  wr = !cs_b & !rw;
  //wire  reset=~res_b;
  wire	[31:0] tod_out;
  //wire [15:0] timer_A;
  
  //Attach modules
  TOD tod1(
    .reset_b(res_b),
    .Hz50(cra[7]),
    .rs(rs),
    .TOD_clk(tod),
    .select_b(cs_b),
    
    .tod_latch(tod_out),
    .rwb(rw),
    .phi2(phi2),
    .db_in(db_in)
  );
/*
  timer timerA(
    .select_b(cs_b),
    .rwb(rw),
    .phi2(phi2),
    .rs(rs),
    .timer(timer_A),
    .timer_in(timer_in),
    .reset_b(res_b)
  );

  timer timerB(
    .timer_latch(timer_latch),
    .reset_b(res_b)
  );*/




  always @ (negedge phi2) 
  begin
  //RESET functions
    if (!res_b) 
    begin
      db_out<=8'h0;
      //ports
      ddra<=8'h0;
      ddrb<=8'h0;   
      pa_out<=8'h0;
      pb_out<=8'h0;


      //TOD

      //TIMER
      
      //Serial port
      
      //Interrupt Control Register
      
      //Control registers
      cra<=8'h0;
      crb<=8'h0;
  end
  else
  begin
      //Read functions
      if(rd)
      begin
        case(rs)
          //Ports
          4'h0 :db_out<=pa_in;
          4'h1 :db_out<=pb_in;
          4'h2 :db_out<=ddra;
          4'h3 :db_out<=ddrb;
          //Timer registers
          //4'h4 :db_out<=8'hee;
          //4'h5 :db_out<=8'h56;
          //4'h6 :db_out<=8'h57;
          //4'h7 :db_out<=8'h58;
          //TOD registers
          4'h8 :db_out<=tod_out[7:0];
          4'h9 :db_out<=tod_out[15:8];
          4'ha :db_out<=tod_out[23:16];
          4'hb :db_out<=tod_out[31:24];
          
          //SDR
          //4'hc :db_out<=8'h90;
          //ICR
          //4'hd :db_out<=8'ha0;
          //Control registers
          4'he :db_out<=cra;
          4'hf :db_out<=crb;
          default: ;
        endcase
      end
    //end
    //Write functions
    if(wr)
    begin
      case (rs)
        4'h0: pa_out  <= db_in;
        4'h1: pb_out  <= db_in;
        4'h2: ddra <= db_in;
        4'h3: ddrb <= db_in;
        4'he: cra <=db_in;
        4'hf: crb <=db_in;
      default: ;
    endcase
  end
  end
  end

endmodule

6526 CIA.srcs/sim_1/new/testbench.v
`timescale 1ns / 1ps
//////////////////////////////////////////////////////////////////////////////////
// Company: 
// Engineer: 
// 
// Create Date: 01/26/2020 06:05:29 PM
// Design Name: 
// Module Name: testbench
// Project Name: 
// Target Devices: 
// Tool Versions: 
// Description: 
// 
// Dependencies: 
// 
// Revision:
// Revision 0.01 - File Created
// Additional Comments:
// 
//////////////////////////////////////////////////////////////////////////////////


module CIA_tb();

  integer x;
  
  reg phi, res_b, cs_b, rw, tod;
  reg [3:0]rs;
  reg [7:0]db_in;
  wire [7:0]db_out;
  
  reg [7:0]pa_in;
  wire [7:0]pa_out;
  reg [7:0]pb_in;
  wire [7:0]pb_out;
  
  //wire ;
  
  CIA cia1(
    .phi2(phi),
    .res_b(res_b),
    .cs_b(cs_b),
    .rw(rw),
    
    .rs(rs),
    .db_in(db_in),
    .db_out(db_out),
    .pa_in(pa_in),
    .pa_out(pa_out),
    .pb_in(pb_in),
    .pb_out(pb_out),
    
    .tod(tod)
  );
  
  
  //Freerunning 1MHz CLK
  always #500 phi=~phi;
  always #1190tod=~tod;
  
   initial begin
     //$dumpfile("out.vcd");
     //$dumpvars(3,CIA_tb);
     //$dumpvars(3,cia1);
     phi=1;
     tod=0;
     res_b=1;
     cs_b=1;
     rw=0;
     rs = 4'h0;
     db_in =8'haa;
     pa_in =8'hff;
     pb_in =8'h0;
     
     //Assert RST
     #1250;
     res_b=0;
     #2500;
     res_b=1;
     #250;
     
     setRSread(4'h00);
     setRSwrite(4'h00,8'hc7);
     
     //set 50Hz
//     setRSwrite(4'he,8'h80);
     
     setRSwrite(4'hb,8'h11);
     setRSwrite(4'ha,8'h59);
     setRSwrite(4'h9,8'h59);
     setRSwrite(4'h8,8'h08);
     
     //setRSread(4'h9);
     //setRSread(4'hb);

     //read TOD
     //setRSread(4'h2);
     //setRSread(4'hb);
     setRSread(4'hb);
     setRSread(4'ha);
     setRSread(4'h9);
     setRSread(4'h8);
     
     //Read TOD via loop
     for (x=4'hb; x>4'h7; x=x-1) 
     begin
       setRSread(x);
     end
     
    /* 
     //Read sec10 repeatedly
     for(x = 0; x<80; x=x+1)
     begin
       setRSread(4'h8);
     end
     */
     
    #90000;
    $finish;
   end
  
  
  
  
  
  
  
  //TASKS
  task setRSread;
    input [3:0] rs_set;
    
    begin
      #50;
      rs=rs_set;
      rw=1;
      #250
      cs_b=0;
      #500;
      cs_b=1;
      #200;
    end
  endtask
  
  task setRSwrite;
    input [3:0] rs_set;
    input [7:0] in_byte;
      
    
    begin
      #50;
      rs=rs_set;
      rw=0;
      db_in=in_byte;
      #250
      cs_b=0;
      #500;
      cs_b=1;
      #200;
    end
  endtask
  
    
  
endmodule

6526 CIA.sim/sim_1/behav/xsim/dump.vcd
$date
   Wed Feb  5 04:19:39 2020
$end
$version
  2019.2
$end
$timescale
  1ps
$end
$scope module CIA_tb $end
$scope module cia1 $end
$var wire 1 ! phi2 $end
$var wire 1 " res_b $end
$var wire 1 # cs_b $end
$var wire 1 $ rw $end
$var wire 4 % rs [3:0] $end
$var wire 8 & db_in [7:0] $end
$var reg 8 ' db_out [7:0] $end
$var wire 8 ( pa_in [7:0] $end
$var reg 8 ) pa_out [7:0] $end
$var wire 8 * pb_in [7:0] $end
$var reg 8 + pb_out [7:0] $end
$var reg 8 , ddra [7:0] $end
$var reg 8 - ddrb [7:0] $end
$var wire 1 . tod $end
$var reg 8 / cra [7:0] $end
$var reg 8 0 crb [7:0] $end
$var wire 1 1 rd $end
$var wire 1 2 wr $end
$var wire 32 3 tod_out [31:0] $end
$scope module tod1 $end
$var wire 1 " reset_b $end
$var wire 1 4 Hz50 $end
$var wire 1 . TOD_clk $end
$var wire 1 # select_b $end
$var wire 1 $ rwb $end
$var wire 1 ! phi2 $end
$var wire 4 % rs [3:0] $end
$var reg 32 5 tod_latch [31:0] $end
$var wire 8 & db_in [7:0] $end
$var reg 3 6 tod_tick_counter [2:0] $end
$var reg 32 7 tod [31:0] $end
$var reg 32 8 alarm [31:0] $end
$var reg 1 9 tod_run $end
$var wire 1 : wr $end
$var wire 1 ; rd $end
$var wire 1 < c1 $end
$var wire 1 = c2 $end
$var wire 1 > c3 $end
$var wire 1 ? c4 $end
$var wire 1 @ c5 $end
$var wire 1 A c6 $end
$upscope $end
$upscope $end
$upscope $end
$enddefinitions $end
#0
$dumpvars
1!
1"
1#
0$
b0 %
b10101010 &
bx '
b11111111 (
bx )
b0 *
bx +
bx ,
bx -
0.
bx /
bx 0
01
02
bx 3
x4
bx 5
bx 6
bx 7
bx 8
x9
0:
0;
x<
x=
x>
x?
x@
xA
$end
#50000
0!
01
02
0:
0;
#100000
1!
01
02
0:
0;
#125000
0"
#150000
0!
b0 '
b0 )
b0 +
b0 ,
b0 -
b0 /
b0 0
01
02
04
0:
0;
#200000
1!
01
02
0:
0;
#250000
0!
b0 /
b0 0
01
02
0:
0;
#300000
1!
01
02
0:
0;
#350000
0!
b0 /
b0 0
01
02
0:
0;
#375000
1"
#400000
1!
1.
01
02
0:
0;
#405000
1$
01
02
0:
0;
#430000
0#
11
02
0:
1;
#450000
0!
01
02
0:
0;
#480000
1#
01
02
0:
0;
#500000
1!
01
02
0:
0;
#505000
0$
b11000111 &
01
02
0:
0;
#530000
0#
01
12
1:
0;
#550000
0!
01
02
0:
0;
#580000
1#
01
02
0:
0;
#600000
1!
01
02
0:
0;
#605000
b1110 %
b10000000 &
#630000
0#
01
12
1:
0;
#650000
0!
01
02
0:
0;
#680000
1#
01
02
0:
0;
#700000
1!
01
02
0:
0;
#705000
b1011 %
b101 &
#730000
0#
01
12
1:
0;
#750000
0!
01
02
0:
0;
#780000
1#
01
02
0:
0;
#800000
1!
0.
01
02
0:
0;
#805000
b1010 %
b1000000 &
#830000
0#
01
12
1:
0;
#850000
0!
01
02
0:
0;
#880000
1#
01
02
0:
0;
#900000
1!
01
02
0:
0;
#905000
b1001 %
b10101 &
#930000
0#
01
12
1:
0;
#950000
0!
01
02
0:
0;
#980000
1#
01
02
0:
0;
#1000000
1!
01
02
0:
0;
